module_config/__init__.py
module_config/main.py
module_config-0.0.1.dist-info/LICENSE
module_config-0.0.1.dist-info/METADATA
module_config-0.0.1.dist-info/WHEEL
module_config-0.0.1.dist-info/top_level.txt
module_config-0.0.1.dist-info/RECORD
