Metadata-Version: 2.1
Name: module_config
Version: 0.0.1
Summary: A simple configuration manager for Python applications.
Home-page: https://github.com/pablove2001/module-config
Author: Pablo Vergara
Author-email: vergarapablo2001@gmail.com
Classifier: Programming Language :: Python :: 3
Classifier: License :: OSI Approved :: MIT License
Classifier: Operating System :: OS Independent
Requires-Python: >=3.12
License-File: LICENSE
Requires-Dist: pyyaml
